aioelectricitymaps/__init__.py
aioelectricitymaps/const.py
aioelectricitymaps/electricitymaps.py
aioelectricitymaps/exceptions.py
aioelectricitymaps/marshmallow.py
aioelectricitymaps/models.py
aioelectricitymaps/py.typed
aielectricitymaps-0.1.0.dist-info/LICENSE
aielectricitymaps-0.1.0.dist-info/METADATA
aielectricitymaps-0.1.0.dist-info/WHEEL
aielectricitymaps-0.1.0.dist-info/RECORD
