Metadata-Version: 2.1
Name: aielectricitymaps
Version: 0.1.0
Summary: Async Python 3 wrapper for Electricity maps
Home-page: https://github.com/jpbede/aioelectricitymaps
License: MIT
Author: Jan-Philipp Benecke
Author-email: jan-philipp@bnck.me
Requires-Python: >=3.10,<4.0
Classifier: License :: OSI Approved :: MIT License
Classifier: Programming Language :: Python :: 3
Classifier: Programming Language :: Python :: 3.10
Classifier: Programming Language :: Python :: 3.11
Requires-Dist: aiohttp (>=3.8.5,<4.0.0)
Requires-Dist: dataclasses-json (>=0.6.1,<0.7.0)
Project-URL: Repository, https://github.com/jpbede/aioelectricitymaps
